{"_id":"map-key","_rev":"12-cb30344166a942aa32acf044127e9774","name":"map-key","time":{"modified":"2014-08-31T18:49:37.345Z","created":"2014-03-27T12:48:14.674Z","0.1.0":"2014-03-27T12:48:14.674Z","0.1.1":"2014-04-02T13:24:33.341Z","0.1.3":"2014-04-30T06:45:15.650Z","0.1.4":"2014-04-30T06:51:38.857Z","0.1.5":"2014-08-31T18:49:37.345Z"},"maintainers":[{"name":"kevva","email":"kevinmartensson@gmail.com"}],"dist-tags":{"latest":"0.1.5"},"description":"Map an object key that ends with a value","readme":"ERROR: No README data found!","versions":{"0.1.5":{"name":"map-key","version":"0.1.5","description":"Map an object key that ends with a value","license":"MIT","repository":{"type":"git","url":"git://github.com/kevva/map-key"},"author":{"name":"Kevin Mårtensson","email":"kevinmartensson@gmail.com","url":"https://github.com/kevva"},"engines":{"node":">=0.10.0"},"scripts":{"test":"mocha --reporter list"},"files":["index.js"],"keywords":["endswith","key","map","object"],"dependencies":{"lodash":"^2.4.1","underscore.string":"^2.3.3"},"devDependencies":{"mocha":"^1.18.2"},"bugs":{"url":"https://github.com/kevva/map-key/issues"},"homepage":"https://github.com/kevva/map-key","_id":"map-key@0.1.5","_shasum":"8afb134f2a321a4de29befcb5aaba3348b37bdfc","_from":".","_npmVersion":"1.4.23","_npmUser":{"name":"kevva","email":"kevinmartensson@gmail.com"},"maintainers":[{"name":"kevva","email":"kevinmartensson@gmail.com"}],"dist":{"shasum":"8afb134f2a321a4de29befcb5aaba3348b37bdfc","tarball":"http://registry.npmjs.org/map-key/-/map-key-0.1.5.tgz"},"directories":{}}},"homepage":"https://github.com/kevva/map-key","keywords":["endswith","key","map","object"],"repository":{"type":"git","url":"git://github.com/kevva/map-key"},"author":{"name":"Kevin Mårtensson","email":"kevinmartensson@gmail.com","url":"https://github.com/kevva"},"bugs":{"url":"https://github.com/kevva/map-key/issues"},"license":"MIT","readmeFilename":"","_attachments":{},"_etag":"\"736BX36H2Z5DGBGB89N3V87L5\""}